Alpha_Planet/Alpha_Rabbit.py
Alpha_Planet/Factor_Calculator.py
Alpha_Planet/Factor_Def_and_Get_Method.py
Alpha_Planet/__init__.py
Alpha_Planet/trade_strategy.py
Alpha_Rabbit/Alpha_Rabbit.py
Alpha_Rabbit/Factor_Calculator.py
Alpha_Rabbit/Factor_Def_and_Get_Method.py
Alpha_Rabbit/__init__.py
Alpha_Rabbit/trade_strategy.py
Alpha_Planet-1.0.1.dist-info/LICENSE.txt
Alpha_Planet-1.0.1.dist-info/METADATA
Alpha_Planet-1.0.1.dist-info/WHEEL
Alpha_Planet-1.0.1.dist-info/top_level.txt
Alpha_Planet-1.0.1.dist-info/zip-safe
Alpha_Planet-1.0.1.dist-info/RECORD
